[
{
    "model": "reviews.review",
    "pk": 1,
    "fields": {
        "post": 1,
        "user": 4,
        "title": "너무 편했어요 ㅠㅠ 감사합니다",
        "content": "<p><img alt=\"\" src=\"https://pcmap.place.naver.com/accommodation/35637335/photo?businessCategory=camping#\" /><img alt=\"\" src=\"https://search.pstatic.net/common/?src=https%3A%2F%2Fldb-phinf.pstatic.net%2F20221021_141%2F1666317271907b7Tpa_JPEG%2F027A2314-HDR.jpg\" style=\"height:853px; width:1280px\" />야경 멋진거 보이시나요?</p>",
        "rating": 4,
        "created_at": "2023-05-17T11:38:51.107Z",
        "updated_at": "2023-05-17T11:38:51.107Z",
        "like_users": [],
        "dislike_users": []
    }
},
{
    "model": "reviews.review",
    "pk": 2,
    "fields": {
        "post": 3,
        "user": 4,
        "title": "단풍구경잘하다갑니다",
        "content": "<p><img alt=\"\" src=\"https://search.pstatic.net/common/?src=https%3A%2F%2Fpup-review-phinf.pstatic.net%2FMjAyMzA1MTRfMjU1%2FMDAxNjg0MDczNzAzODc4.4JuZorCTiNwYdIxHgRf83C0A4d07S3AY8hYo7bUiwdYg.FEzlbz4V0plVuNqmsPKD8eAFTGsqTzYiAxQkcUr166gg.JPEG%2FIMG_0076.jpeg\" style=\"height:1280px; width:960px\" />캬 멋지죠</p>",
        "rating": 4,
        "created_at": "2023-05-17T11:44:40.275Z",
        "updated_at": "2023-05-17T11:44:40.275Z",
        "like_users": [
            4
        ],
        "dislike_users": []
    }
},
{
    "model": "reviews.review",
    "pk": 3,
    "fields": {
        "post": 6,
        "user": 4,
        "title": "어땠을까 가격이 좀만더 저렴했더라면",
        "content": "<p>만약 그랬더라면&nbsp;</p>",
        "rating": 3,
        "created_at": "2023-05-17T11:48:42.195Z",
        "updated_at": "2023-05-17T11:48:42.195Z",
        "like_users": [],
        "dislike_users": []
    }
},
{
    "model": "reviews.review",
    "pk": 4,
    "fields": {
        "post": 30,
        "user": 5,
        "title": "너무 예뻐요",
        "content": "<p>너무 좋아요 다시 올 것 같아요</p>",
        "rating": 4,
        "created_at": "2023-05-17T12:30:01.193Z",
        "updated_at": "2023-05-17T12:30:01.193Z",
        "like_users": [
            14
        ],
        "dislike_users": []
    }
},
{
    "model": "reviews.review",
    "pk": 5,
    "fields": {
        "post": 27,
        "user": 5,
        "title": "굿굿",
        "content": "<p>아주 굿이에요</p>",
        "rating": 5,
        "created_at": "2023-05-17T12:30:27.518Z",
        "updated_at": "2023-05-17T12:30:27.518Z",
        "like_users": [
            5
        ],
        "dislike_users": []
    }
},
{
    "model": "reviews.review",
    "pk": 6,
    "fields": {
        "post": 24,
        "user": 5,
        "title": "무조건 다시",
        "content": "<p>무조건 다시 올 거에요 자연환경이 진짜 너무 예뻐서 보기만 해도 기분이 좋아요</p>",
        "rating": 5,
        "created_at": "2023-05-17T12:31:04.324Z",
        "updated_at": "2023-05-17T12:31:04.324Z",
        "like_users": [],
        "dislike_users": []
    }
},
{
    "model": "reviews.review",
    "pk": 7,
    "fields": {
        "post": 26,
        "user": 5,
        "title": "good",
        "content": "<p>사람들도 많고 해서 복잡할 줄 알았는데 너무 좋아요</p>",
        "rating": 5,
        "created_at": "2023-05-17T12:32:02.354Z",
        "updated_at": "2023-05-17T12:32:02.355Z",
        "like_users": [],
        "dislike_users": []
    }
},
{
    "model": "reviews.review",
    "pk": 8,
    "fields": {
        "post": 32,
        "user": 7,
        "title": "호수 좋아요",
        "content": "<p>보고싶은 마음 호수만 하니 눈 감을 밖에</p>",
        "rating": 4,
        "created_at": "2023-05-17T12:35:25.955Z",
        "updated_at": "2023-05-17T12:35:25.955Z",
        "like_users": [
            7,
            12
        ],
        "dislike_users": []
    }
},
{
    "model": "reviews.review",
    "pk": 9,
    "fields": {
        "post": 31,
        "user": 7,
        "title": "강진에서 막걸리 한잔",
        "content": "<p>난 이제 지쳤어요</p>",
        "rating": 5,
        "created_at": "2023-05-17T12:37:01.943Z",
        "updated_at": "2023-05-17T12:37:01.943Z",
        "like_users": [],
        "dislike_users": []
    }
},
{
    "model": "reviews.review",
    "pk": 10,
    "fields": {
        "post": 2,
        "user": 7,
        "title": "카라반 너무 좋아요",
        "content": "<p>오늘 소개할 노래는. 아라비아 풍의 스탠다드 재즈곡으로 유명한. CARAVAN 입니다. Juan Tizol 이 작곡하고,. Duke Ellington이 초연한.</p>",
        "rating": 5,
        "created_at": "2023-05-17T12:39:57.001Z",
        "updated_at": "2023-05-17T12:56:50.476Z",
        "like_users": [],
        "dislike_users": []
    }
},
{
    "model": "reviews.review",
    "pk": 11,
    "fields": {
        "post": 1,
        "user": 5,
        "title": "너무 편합니다",
        "content": "<p>너무 편하게 있다가 갔어요~</p>",
        "rating": 5,
        "created_at": "2023-05-17T12:40:05.159Z",
        "updated_at": "2023-05-17T12:40:05.159Z",
        "like_users": [],
        "dislike_users": []
    }
},
{
    "model": "reviews.review",
    "pk": 12,
    "fields": {
        "post": 36,
        "user": 7,
        "title": "금강에 살으리랏다",
        "content": "<p>운무 데리고 금강에 살으리랏다 홍진에 썩은 명리야 아는체나 하리요</p>",
        "rating": 4,
        "created_at": "2023-05-17T12:41:09.588Z",
        "updated_at": "2023-05-17T12:41:09.588Z",
        "like_users": [],
        "dislike_users": []
    }
},
{
    "model": "reviews.review",
    "pk": 13,
    "fields": {
        "post": 23,
        "user": 7,
        "title": "이름대로 멋진 곳이에요",
        "content": "<p>차라리 잘 된 거야 그래 그렇게 믿을래</p>",
        "rating": 5,
        "created_at": "2023-05-17T12:44:06.220Z",
        "updated_at": "2023-05-17T12:44:06.220Z",
        "like_users": [],
        "dislike_users": []
    }
},
{
    "model": "reviews.review",
    "pk": 14,
    "fields": {
        "post": 24,
        "user": 8,
        "title": "경치가..!",
        "content": "<p>경치가 너무 좋습니다.</p>\r\n\r\n<p>자연속에서 건강해지는 느낌..!!</p>",
        "rating": 5,
        "created_at": "2023-05-17T12:48:13.872Z",
        "updated_at": "2023-05-17T12:48:13.872Z",
        "like_users": [],
        "dislike_users": []
    }
},
{
    "model": "reviews.review",
    "pk": 15,
    "fields": {
        "post": 38,
        "user": 9,
        "title": "미쳤어요",
        "content": "<p>미쳤어요 아주 무조건 다시 갈겁니다</p>",
        "rating": 5,
        "created_at": "2023-05-17T12:51:59.179Z",
        "updated_at": "2023-05-17T12:51:59.179Z",
        "like_users": [
            6,
            9
        ],
        "dislike_users": []
    }
},
{
    "model": "reviews.review",
    "pk": 16,
    "fields": {
        "post": 38,
        "user": 6,
        "title": "너무 이뻐요",
        "content": "<p>숲속에 있어서 너무 이쁘고&nbsp;</p>\r\n\r\n<p>힐링하고 왔습니다 : )</p>",
        "rating": 5,
        "created_at": "2023-05-17T12:53:10.432Z",
        "updated_at": "2023-05-17T12:53:10.433Z",
        "like_users": [
            6
        ],
        "dislike_users": []
    }
},
{
    "model": "reviews.review",
    "pk": 17,
    "fields": {
        "post": 38,
        "user": 7,
        "title": "이름처럼 풀이 많고 아름다워요",
        "content": "<p><img alt=\"\" src=\"http://choriforest.co.kr/theme/template1/img/41_1.png\" style=\"height:445px; width:672px\" /></p>\r\n\r\n<p>너무 좋아요 아름답죠?</p>",
        "rating": 5,
        "created_at": "2023-05-17T12:53:24.160Z",
        "updated_at": "2023-05-17T12:53:46.395Z",
        "like_users": [
            5,
            6,
            7
        ],
        "dislike_users": []
    }
},
{
    "model": "reviews.review",
    "pk": 18,
    "fields": {
        "post": 2,
        "user": 10,
        "title": "음....",
        "content": "<p>음...생각보다..?</p>",
        "rating": 2,
        "created_at": "2023-05-17T12:53:48.394Z",
        "updated_at": "2023-05-17T12:53:48.394Z",
        "like_users": [],
        "dislike_users": []
    }
},
{
    "model": "reviews.review",
    "pk": 19,
    "fields": {
        "post": 23,
        "user": 10,
        "title": "음..?",
        "content": "<p>예쁘긴 한데.,...흠</p>",
        "rating": 3,
        "created_at": "2023-05-17T12:55:19.956Z",
        "updated_at": "2023-05-17T12:55:19.956Z",
        "like_users": [],
        "dislike_users": []
    }
},
{
    "model": "reviews.review",
    "pk": 20,
    "fields": {
        "post": 31,
        "user": 10,
        "title": "흠?",
        "content": "<p>흠흠....</p>",
        "rating": 3,
        "created_at": "2023-05-17T12:56:10.225Z",
        "updated_at": "2023-05-17T12:56:10.225Z",
        "like_users": [],
        "dislike_users": []
    }
},
{
    "model": "reviews.review",
    "pk": 21,
    "fields": {
        "post": 38,
        "user": 11,
        "title": "토리와 비슷한 초리 이름부터 마음에 들어요",
        "content": "<p>이쁘고 ... 조용하고 ... 한산하고. .. 마음에 평화 ... 그 자체 .. 행복</p>",
        "rating": 5,
        "created_at": "2023-05-17T12:56:39.840Z",
        "updated_at": "2023-05-17T12:56:39.840Z",
        "like_users": [
            5
        ],
        "dislike_users": []
    }
},
{
    "model": "reviews.review",
    "pk": 22,
    "fields": {
        "post": 24,
        "user": 10,
        "title": "예쁘긴 하네요",
        "content": "<p>예쁘긴 하네요?</p>",
        "rating": 4,
        "created_at": "2023-05-17T12:56:43.462Z",
        "updated_at": "2023-05-17T12:56:43.462Z",
        "like_users": [],
        "dislike_users": []
    }
},
{
    "model": "reviews.review",
    "pk": 23,
    "fields": {
        "post": 27,
        "user": 10,
        "title": "깔끔하고 좋네요",
        "content": "<p>깔끔하고 좋아요</p>",
        "rating": 4,
        "created_at": "2023-05-17T12:57:07.677Z",
        "updated_at": "2023-05-17T12:57:07.677Z",
        "like_users": [],
        "dislike_users": []
    }
},
{
    "model": "reviews.review",
    "pk": 24,
    "fields": {
        "post": 38,
        "user": 8,
        "title": "최고최고요",
        "content": "<p>두번째 방문입니다.</p>\r\n\r\n<p>사이트가 단독느낌이라 좋습니다. 주말에는 오후3시부터 미꾸라지 잡기 체험프로그램으로 아이와 함께 즐거운 시간을 보냈습니다.</p>\r\n\r\n<p>뜰채와 고기담는통이 필요하니 참고하세요^^</p>\r\n\r\n<p>뜰채 사이즈는 중소형으로 챙기시기 바랍니다. 주말 프로그램으로만 체험가능합니다</p>\r\n\r\n<p>내부에는 관리동과 매점이 붙어있고, 카페동은 별도로 있습니다. 카페동 내부에서는 커피, 생맥주와 피자, 핫도그를 맛볼 수 있습니다.</p>\r\n\r\n<p>저녁 8시에는 빔프로젝트를 이용하여, 비긴어게인을 틀어주어서 낭만분위기를 한껏 더 즐길 수 있습니다.</p>\r\n\r\n<p>펜현동이라 높은것에서 바라보는 그 느낌 아니까~</p>\r\n\r\n<p>테라스외부에서 바비큐를 즐기고, 깨끗한 공기와 아카시아 향이 나는 초리포레스트를 강력 추천합니다.</p>\r\n\r\n<p><img alt=\"\" src=\"/media/uploads/2023/05/17/33.jpg\" style=\"height:300px; width:300px\" /><img alt=\"\" src=\"/media/uploads/2023/05/17/34.jpg\" style=\"height:300px; width:300px\" /><img alt=\"\" src=\"/media/uploads/2023/05/17/32.jpg\" style=\"height:300px; width:300px\" /></p>",
        "rating": 5,
        "created_at": "2023-05-17T13:00:50.638Z",
        "updated_at": "2023-05-17T13:31:27.299Z",
        "like_users": [
            8,
            12,
            15
        ],
        "dislike_users": []
    }
},
{
    "model": "reviews.review",
    "pk": 25,
    "fields": {
        "post": 26,
        "user": 12,
        "title": "좋군요",
        "content": "<p>아주 좋군요</p>",
        "rating": 4,
        "created_at": "2023-05-17T13:23:52.781Z",
        "updated_at": "2023-05-17T13:23:52.781Z",
        "like_users": [],
        "dislike_users": []
    }
},
{
    "model": "reviews.review",
    "pk": 26,
    "fields": {
        "post": 38,
        "user": 13,
        "title": "너무너무 좋아요",
        "content": "<p>추천받아서 와봤는데 진짜 너무 너무 좋고 너무 행복했어요~ ^^</p>\r\n\r\n<p><img alt=\"\" src=\"/media/uploads/2023/05/17/1.jpg\" style=\"height:300px; width:300px\" /></p>",
        "rating": 5,
        "created_at": "2023-05-17T13:28:17.488Z",
        "updated_at": "2023-05-17T13:30:05.519Z",
        "like_users": [
            5
        ],
        "dislike_users": []
    }
},
{
    "model": "reviews.review",
    "pk": 27,
    "fields": {
        "post": 38,
        "user": 12,
        "title": "최고최고에요!!",
        "content": "<p>좋아요</p>",
        "rating": 5,
        "created_at": "2023-05-17T13:28:57.980Z",
        "updated_at": "2023-05-17T13:28:57.980Z",
        "like_users": [],
        "dislike_users": []
    }
},
{
    "model": "reviews.review",
    "pk": 28,
    "fields": {
        "post": 35,
        "user": 11,
        "title": "이름만큼 장소도 아름다운 곳",
        "content": "<p style=\"text-align:justify\"><img alt=\"\" src=\"/media/uploads/2023/05/17/dotory5.jpg\" style=\"float:right; height:400px; width:300px\" />빵이랑 음료사서 갔어요&nbsp;</p>\r\n\r\n<p style=\"text-align:justify\">매일 일에만 치어 살다가 가끔 이렇게 캠핑가서&nbsp;</p>\r\n\r\n<p style=\"text-align:justify\">바람 쐬어주고 맛있는거 먹어주면</p>\r\n\r\n<p style=\"text-align:justify\">이런게 사는 거다 싶네요 ㅎㅎㅎㅎ</p>\r\n\r\n<p style=\"text-align:justify\">또 오고 싶은&nbsp; 곳이예요 :)</p>",
        "rating": 5,
        "created_at": "2023-05-17T13:29:38.571Z",
        "updated_at": "2023-05-17T13:29:38.571Z",
        "like_users": [],
        "dislike_users": []
    }
},
{
    "model": "reviews.review",
    "pk": 29,
    "fields": {
        "post": 38,
        "user": 14,
        "title": "두번째 방문입니다",
        "content": "<p>&nbsp;</p>\r\n\r\n<p><img alt=\"\" src=\"https://pup-review-phinf.pstatic.net/MjAyMzA0MjRfMTk0/MDAxNjgyMzE1MzkzMTc0._KrBXpNpM-qz-MpOddFiUpkoI8zPWCXe_mCdK9WHRFQg.xAZ7RgBqvOx7RCIX_-YHEKvdxR_l-nui2NNQVS6f1skg.JPEG/1682315372223.jpg?type=w828_60_sharpen\" /></p>\r\n\r\n<p>두 번째 방문이예요. 평일에다 데크가 두 곳만 있어서 완전 황제캠프랍니다. 시설도 깨끗하고 편안히 푹 쉬다갈 수 있어요.</p>",
        "rating": 5,
        "created_at": "2023-05-17T13:30:25.789Z",
        "updated_at": "2023-05-17T13:30:25.789Z",
        "like_users": [
            5
        ],
        "dislike_users": []
    }
},
{
    "model": "reviews.review",
    "pk": 30,
    "fields": {
        "post": 27,
        "user": 13,
        "title": "너무 너무 좋아요~~",
        "content": "<p>처음 와봤는데 너무 만족^^</p>",
        "rating": 4,
        "created_at": "2023-05-17T13:31:23.343Z",
        "updated_at": "2023-05-17T13:31:23.343Z",
        "like_users": [],
        "dislike_users": []
    }
},
{
    "model": "reviews.review",
    "pk": 31,
    "fields": {
        "post": 1,
        "user": 14,
        "title": "사실 전 초리포레스트보다 여기가 더 좋음",
        "content": "<p>사실 전 초리포레스트보다 여기가 더 좋음</p>",
        "rating": 5,
        "created_at": "2023-05-17T13:32:38.450Z",
        "updated_at": "2023-05-17T13:32:38.450Z",
        "like_users": [],
        "dislike_users": []
    }
},
{
    "model": "reviews.review",
    "pk": 32,
    "fields": {
        "post": 6,
        "user": 5,
        "title": "바베큐 좋아요~",
        "content": "<p>바베큐 너무 좋아요~~</p>",
        "rating": 3,
        "created_at": "2023-05-17T13:34:57.972Z",
        "updated_at": "2023-05-17T13:34:57.972Z",
        "like_users": [],
        "dislike_users": []
    }
},
{
    "model": "reviews.review",
    "pk": 33,
    "fields": {
        "post": 38,
        "user": 15,
        "title": "좋아요",
        "content": "<p>좋은데요???</p>",
        "rating": 4,
        "created_at": "2023-05-17T13:36:13.513Z",
        "updated_at": "2023-05-17T13:36:13.513Z",
        "like_users": [
            5,
            8
        ],
        "dislike_users": []
    }
},
{
    "model": "reviews.review",
    "pk": 34,
    "fields": {
        "post": 32,
        "user": 15,
        "title": "그럭저럭 괜찮습니다",
        "content": "<p>굿</p>",
        "rating": 4,
        "created_at": "2023-05-17T13:37:37.536Z",
        "updated_at": "2023-05-17T13:37:37.536Z",
        "like_users": [],
        "dislike_users": []
    }
},
{
    "model": "reviews.review",
    "pk": 35,
    "fields": {
        "post": 30,
        "user": 15,
        "title": "분위기 좋아요",
        "content": "<p>좋아요</p>",
        "rating": 5,
        "created_at": "2023-05-17T13:39:15.919Z",
        "updated_at": "2023-05-17T13:39:15.919Z",
        "like_users": [],
        "dislike_users": []
    }
},
{
    "model": "reviews.review",
    "pk": 36,
    "fields": {
        "post": 38,
        "user": 5,
        "title": "가봤던 곳 중에 가장 좋아요",
        "content": "<p>가장 깨끗하고 가장 쉬기 좋고 시설도 제일 좋았어요</p>\r\n\r\n<p><img alt=\"\" src=\"/media/uploads/2023/05/17/3_Ql5bjmJ.jpg\" style=\"height:300px; width:300px\" /></p>",
        "rating": 5,
        "created_at": "2023-05-17T13:39:30.743Z",
        "updated_at": "2023-05-17T13:39:30.743Z",
        "like_users": [],
        "dislike_users": []
    }
},
{
    "model": "reviews.review",
    "pk": 37,
    "fields": {
        "post": 38,
        "user": 16,
        "title": "현직 캠핑왕입니다",
        "content": "<p>별점 5점드리겠습니다</p>",
        "rating": 5,
        "created_at": "2023-05-17T13:39:33.019Z",
        "updated_at": "2023-05-17T13:39:33.019Z",
        "like_users": [
            8
        ],
        "dislike_users": []
    }
},
{
    "model": "reviews.review",
    "pk": 38,
    "fields": {
        "post": 4,
        "user": 15,
        "title": "쏘쏘",
        "content": "<p>ㅇ</p>",
        "rating": 3,
        "created_at": "2023-05-17T14:02:42.957Z",
        "updated_at": "2023-05-17T14:02:42.957Z",
        "like_users": [],
        "dislike_users": []
    }
},
{
    "model": "reviews.review",
    "pk": 39,
    "fields": {
        "post": 23,
        "user": 5,
        "title": "가족들이랑 오기 좋네요~",
        "content": "<p>어린아이들도 뛰어다니고 분위기가 발랄해서 좋아요~</p>",
        "rating": 3,
        "created_at": "2023-05-17T14:06:26.084Z",
        "updated_at": "2023-05-17T14:06:26.084Z",
        "like_users": [],
        "dislike_users": []
    }
},
{
    "model": "reviews.review",
    "pk": 40,
    "fields": {
        "post": 13,
        "user": 15,
        "title": "굿",
        "content": "<p>굿굿</p>",
        "rating": 4,
        "created_at": "2023-05-17T14:07:03.973Z",
        "updated_at": "2023-05-17T14:07:03.973Z",
        "like_users": [],
        "dislike_users": []
    }
},
{
    "model": "reviews.review",
    "pk": 41,
    "fields": {
        "post": 12,
        "user": 5,
        "title": "매너타임을....",
        "content": "<p>매너타임을 안지키는 문제가 있었네요...</p>",
        "rating": 3,
        "created_at": "2023-05-17T14:09:00.406Z",
        "updated_at": "2023-05-17T14:09:00.406Z",
        "like_users": [],
        "dislike_users": []
    }
},
{
    "model": "reviews.review",
    "pk": 42,
    "fields": {
        "post": 9,
        "user": 15,
        "title": "굿",
        "content": "<p>굿굿</p>",
        "rating": 4,
        "created_at": "2023-05-17T14:09:38.246Z",
        "updated_at": "2023-05-17T14:09:38.246Z",
        "like_users": [],
        "dislike_users": []
    }
},
{
    "model": "reviews.review",
    "pk": 43,
    "fields": {
        "post": 14,
        "user": 15,
        "title": "굿",
        "content": "<p>굿굿</p>",
        "rating": 5,
        "created_at": "2023-05-17T14:11:12.640Z",
        "updated_at": "2023-05-17T14:11:12.640Z",
        "like_users": [],
        "dislike_users": []
    }
},
{
    "model": "reviews.review",
    "pk": 44,
    "fields": {
        "post": 18,
        "user": 15,
        "title": "굿",
        "content": "<p>굿굿</p>",
        "rating": 5,
        "created_at": "2023-05-17T14:11:38.347Z",
        "updated_at": "2023-05-17T14:11:38.347Z",
        "like_users": [],
        "dislike_users": []
    }
},
{
    "model": "reviews.review",
    "pk": 45,
    "fields": {
        "post": 20,
        "user": 15,
        "title": "굿",
        "content": "<p>굿굿</p>",
        "rating": 5,
        "created_at": "2023-05-17T14:11:57.603Z",
        "updated_at": "2023-05-17T14:11:57.603Z",
        "like_users": [],
        "dislike_users": []
    }
},
{
    "model": "reviews.review",
    "pk": 46,
    "fields": {
        "post": 25,
        "user": 5,
        "title": "계곡에서 놀기 좋아요",
        "content": "<p>계곡에서 놀다가 왔다갔다 하기 좋네용</p>",
        "rating": 4,
        "created_at": "2023-05-17T14:12:10.300Z",
        "updated_at": "2023-05-17T14:12:10.300Z",
        "like_users": [],
        "dislike_users": []
    }
},
{
    "model": "reviews.review",
    "pk": 47,
    "fields": {
        "post": 21,
        "user": 15,
        "title": "굿",
        "content": "<p>굿입니다</p>",
        "rating": 4,
        "created_at": "2023-05-17T14:12:14.061Z",
        "updated_at": "2023-05-17T14:12:14.061Z",
        "like_users": [],
        "dislike_users": []
    }
},
{
    "model": "reviews.review",
    "pk": 48,
    "fields": {
        "post": 9,
        "user": 5,
        "title": "시설이 너무 좋아요",
        "content": "<p>개별 바베큐, 시설 빠질 것 하나 없네요</p>",
        "rating": 4,
        "created_at": "2023-05-17T14:13:22.899Z",
        "updated_at": "2023-05-17T14:13:22.900Z",
        "like_users": [],
        "dislike_users": []
    }
},
{
    "model": "reviews.review",
    "pk": 49,
    "fields": {
        "post": 29,
        "user": 11,
        "title": "노루벌이 !!!",
        "content": "<p>벌이 호로롤로로롤로로 날아갔어요&nbsp;</p>",
        "rating": 5,
        "created_at": "2023-05-17T14:15:15.151Z",
        "updated_at": "2023-05-17T14:15:15.151Z",
        "like_users": [],
        "dislike_users": []
    }
},
{
    "model": "reviews.review",
    "pk": 50,
    "fields": {
        "post": 24,
        "user": 15,
        "title": "좋습니다",
        "content": "<p>좋아요좋아요</p>",
        "rating": 5,
        "created_at": "2023-05-17T14:15:18.742Z",
        "updated_at": "2023-05-17T14:15:18.742Z",
        "like_users": [],
        "dislike_users": []
    }
},
{
    "model": "reviews.review",
    "pk": 51,
    "fields": {
        "post": 22,
        "user": 11,
        "title": "얼음골",
        "content": "<p>이름이 얼음골이라서 그런지</p>\r\n\r\n<p>밤에 얼음골 처럼 춥더라구요&nbsp;</p>\r\n\r\n<p>하지만 나머지는 괜찮았어요&nbsp;</p>",
        "rating": 4,
        "created_at": "2023-05-17T14:15:45.538Z",
        "updated_at": "2023-05-17T14:15:45.538Z",
        "like_users": [],
        "dislike_users": []
    }
},
{
    "model": "reviews.review",
    "pk": 52,
    "fields": {
        "post": 27,
        "user": 15,
        "title": "깔끔하고 좋습니다",
        "content": "<p>좋습니다</p>",
        "rating": 5,
        "created_at": "2023-05-17T14:16:06.105Z",
        "updated_at": "2023-05-17T14:16:06.105Z",
        "like_users": [],
        "dislike_users": []
    }
},
{
    "model": "reviews.review",
    "pk": 53,
    "fields": {
        "post": 19,
        "user": 11,
        "title": "온국민 여가 가능한 캠핑장",
        "content": "<p>넓고 아주 좋아요</p>",
        "rating": 4,
        "created_at": "2023-05-17T14:16:12.597Z",
        "updated_at": "2023-05-17T14:16:12.597Z",
        "like_users": [],
        "dislike_users": []
    }
},
{
    "model": "reviews.review",
    "pk": 54,
    "fields": {
        "post": 5,
        "user": 9,
        "title": "가족들이랑 오기 좋았지만...",
        "content": "<p>시설이 생각보다 좀 별로였어요</p>",
        "rating": 3,
        "created_at": "2023-05-17T14:16:33.777Z",
        "updated_at": "2023-05-17T14:16:33.777Z",
        "like_users": [],
        "dislike_users": []
    }
},
{
    "model": "reviews.review",
    "pk": 55,
    "fields": {
        "post": 17,
        "user": 11,
        "title": "제주도 까지 와서",
        "content": "<p>캠핑장 오는 사람이 있다 ?! 그게 바로 나야 나&nbsp;</p>",
        "rating": 4,
        "created_at": "2023-05-17T14:16:36.572Z",
        "updated_at": "2023-05-17T14:16:36.572Z",
        "like_users": [],
        "dislike_users": []
    }
},
{
    "model": "reviews.review",
    "pk": 56,
    "fields": {
        "post": 1,
        "user": 15,
        "title": "아늑해요",
        "content": "<p>굿</p>",
        "rating": 5,
        "created_at": "2023-05-17T14:16:41.701Z",
        "updated_at": "2023-05-17T14:16:41.701Z",
        "like_users": [],
        "dislike_users": []
    }
},
{
    "model": "reviews.review",
    "pk": 57,
    "fields": {
        "post": 15,
        "user": 11,
        "title": "해솔길.....",
        "content": "<p>솔길.....해 ..... 솔길.....</p>\r\n\r\n<p>해 그리고 솔길.....</p>\r\n\r\n<p>낭만 넘치는 이곳..</p>",
        "rating": 4,
        "created_at": "2023-05-17T14:17:01.080Z",
        "updated_at": "2023-05-17T14:17:01.080Z",
        "like_users": [],
        "dislike_users": []
    }
},
{
    "model": "reviews.review",
    "pk": 58,
    "fields": {
        "post": 10,
        "user": 11,
        "title": "제 1캠핑장도 있나요?",
        "content": "<p>있어도 2캠핑장 올것임 ㅎㅎㅎㅎㅎ</p>",
        "rating": 4,
        "created_at": "2023-05-17T14:17:25.979Z",
        "updated_at": "2023-05-17T14:17:25.979Z",
        "like_users": [],
        "dislike_users": []
    }
},
{
    "model": "reviews.review",
    "pk": 59,
    "fields": {
        "post": 11,
        "user": 9,
        "title": "여길 이제 오다니",
        "content": "<p>미리 알지 못했던 시간이 아까워요</p>",
        "rating": 4,
        "created_at": "2023-05-17T14:17:31.273Z",
        "updated_at": "2023-05-17T14:17:31.273Z",
        "like_users": [],
        "dislike_users": []
    }
},
{
    "model": "reviews.review",
    "pk": 60,
    "fields": {
        "post": 34,
        "user": 11,
        "title": "분명 어 ...? 주차장 하셨을 것인데",
        "content": "<p>저도 그랬음</p>\r\n\r\n<p>하지만 수달 봄&nbsp;</p>\r\n\r\n<p>수달 보고싶으면 와도됨&nbsp;</p>",
        "rating": 4,
        "created_at": "2023-05-17T14:17:48.779Z",
        "updated_at": "2023-05-17T14:17:48.779Z",
        "like_users": [],
        "dislike_users": []
    }
},
{
    "model": "reviews.review",
    "pk": 61,
    "fields": {
        "post": 24,
        "user": 12,
        "title": "풍경이 와",
        "content": "<p>ㄱ</p>",
        "rating": 5,
        "created_at": "2023-05-17T14:17:52.157Z",
        "updated_at": "2023-05-17T14:17:52.157Z",
        "like_users": [],
        "dislike_users": []
    }
},
{
    "model": "reviews.review",
    "pk": 62,
    "fields": {
        "post": 7,
        "user": 9,
        "title": "자연은 좋지만",
        "content": "<p>너무 좁고 시설이....</p>",
        "rating": 3,
        "created_at": "2023-05-17T14:18:02.549Z",
        "updated_at": "2023-05-17T14:18:02.549Z",
        "like_users": [],
        "dislike_users": []
    }
},
{
    "model": "reviews.review",
    "pk": 63,
    "fields": {
        "post": 28,
        "user": 11,
        "title": "알프스를 품고있다",
        "content": "<p>풍경이 아름답고 외국인지 한국인지&nbsp;</p>\r\n\r\n<p>한숨 한번에 상쾌한 공기 한번 들이쉬면</p>\r\n\r\n<p>근심이 싹</p>",
        "rating": 5,
        "created_at": "2023-05-17T14:18:24.006Z",
        "updated_at": "2023-05-17T14:18:24.006Z",
        "like_users": [],
        "dislike_users": []
    }
},
{
    "model": "reviews.review",
    "pk": 64,
    "fields": {
        "post": 27,
        "user": 12,
        "title": "대형 수영장 최고!",
        "content": "<p>ㄱ</p>",
        "rating": 5,
        "created_at": "2023-05-17T14:18:29.173Z",
        "updated_at": "2023-05-17T14:18:29.173Z",
        "like_users": [],
        "dislike_users": []
    }
},
{
    "model": "reviews.review",
    "pk": 65,
    "fields": {
        "post": 8,
        "user": 11,
        "title": "밀 양 ?!",
        "content": "<p>밀 양이 운영하는곳...?!</p>",
        "rating": 4,
        "created_at": "2023-05-17T14:18:42.539Z",
        "updated_at": "2023-05-17T14:18:42.539Z",
        "like_users": [],
        "dislike_users": []
    }
},
{
    "model": "reviews.review",
    "pk": 66,
    "fields": {
        "post": 8,
        "user": 9,
        "title": "좋아요~",
        "content": "<p>가족들이랑 오기도 친구들이랑 오기도 좋아요</p>",
        "rating": 4,
        "created_at": "2023-05-17T14:18:53.429Z",
        "updated_at": "2023-05-17T14:18:53.429Z",
        "like_users": [],
        "dislike_users": []
    }
},
{
    "model": "reviews.review",
    "pk": 67,
    "fields": {
        "post": 24,
        "user": 16,
        "title": "경치 좋아요 벌써 17번째 방문입니다",
        "content": "<p>좋아요</p>",
        "rating": 5,
        "created_at": "2023-05-17T14:19:44.154Z",
        "updated_at": "2023-05-17T14:19:44.154Z",
        "like_users": [],
        "dislike_users": []
    }
}
]
